netconf_lnu/__init__.py
netconf_lnu/braslogger.py
netconf_lnu/main.py
netconf_lnu/mytest.py
netconf_lnu/netconf.py
netconf_lnu/snmp.py
netconf_lnu-2025.1.16.1.dist-info/METADATA
netconf_lnu-2025.1.16.1.dist-info/WHEEL
netconf_lnu-2025.1.16.1.dist-info/entry_points.txt
netconf_lnu-2025.1.16.1.dist-info/licenses/LICENSE
netconf_lnu-2025.1.16.1.dist-info/RECORD
