Metadata-Version: 2.4
Name: netconf-lnu
Version: 2025.1.16.1
Summary: Python Scripts to get schema YANG files from network device
Project-URL: Source, https://github.com/mengbo/netconf-lnu
Author-email: Meng Bo <mengbo@lnu.edu.cn>
License: MIT
License-File: LICENSE
Requires-Python: >=3.11
Requires-Dist: ncclient>=0.6.16
Requires-Dist: puresnmp>=2.0.1
Requires-Dist: xmltodict>=0.14.2
